.gitattributes
AUTHORS
ChangeLog
LICENSE
MANIFEST.in
Makefile
README.md
__init__.py
requirements.txt
setup.cfg
setup.py
.github/workflows/github_build.yml
.vscode/launch.json
catPyNet/Utilities.py
catPyNet/__init__.py
catPyNet/algorithm/AlgorithmBase.py
catPyNet/algorithm/CoreRAFAlgorithm.py
catPyNet/algorithm/Importance.py
catPyNet/algorithm/MaxCAFAlgorithm.py
catPyNet/algorithm/MaxPseudoRAFAlgorithm.py
catPyNet/algorithm/MaxRAFAlgorithm.py
catPyNet/algorithm/MinIRAFHeuristic.py
catPyNet/algorithm/__init__.py
catPyNet/fileIO/GraphIO.py
catPyNet/fileIO/IOManager.py
catPyNet/fileIO/ModelIO.py
catPyNet/fileIO/__init__.py
catPyNet/main/CatPyNet.py
catPyNet/main/__init__.py
catPyNet/model/DisjunctiveNormalForm.py
catPyNet/model/MoleculeType.py
catPyNet/model/Reaction.py
catPyNet/model/ReactionSystem.py
catPyNet/model/__init__.py
catPyNet/settings/ArrowNotation.py
catPyNet/settings/ReactionNotation.py
catPyNet/settings/__init__.py
catPyNet/tests/__init__.py
catPyNet/tests/test_advanced.py
catPyNet/tests/test_basic.py
catPyNet/tools/CommandLineTool.py
catPyNet/tools/PolymerTool.py
catPyNet/tools/__init__.py
catpynet/Utilities.py
catpynet/__init__.py
catpynet.egg-info/PKG-INFO
catpynet.egg-info/SOURCES.txt
catpynet.egg-info/dependency_links.txt
catpynet.egg-info/not-zip-safe
catpynet.egg-info/pbr.json
catpynet.egg-info/requires.txt
catpynet.egg-info/top_level.txt
catpynet/algorithm/AlgorithmBase.py
catpynet/algorithm/CoreRAFAlgorithm.py
catpynet/algorithm/Importance.py
catpynet/algorithm/MaxCAFAlgorithm.py
catpynet/algorithm/MaxPseudoRAFAlgorithm.py
catpynet/algorithm/MaxRAFAlgorithm.py
catpynet/algorithm/MinIRAFHeuristic.py
catpynet/algorithm/__init__.py
catpynet/fileIO/GraphIO.py
catpynet/fileIO/IOManager.py
catpynet/fileIO/ModelIO.py
catpynet/fileIO/__init__.py
catpynet/main/CatPyNet.py
catpynet/main/__init__.py
catpynet/model/DisjunctiveNormalForm.py
catpynet/model/MoleculeType.py
catpynet/model/Reaction.py
catpynet/model/ReactionSystem.py
catpynet/model/__init__.py
catpynet/settings/ArrowNotation.py
catpynet/settings/ReactionNotation.py
catpynet/settings/__init__.py
catpynet/tests/__init__.py
catpynet/tests/test_advanced.py
catpynet/tests/test_basic.py
