Metadata-Version: 2.1
Name: catpynet
Version: 1.0.2
Summary: CatPyNet is a lean tool for computations on reaction systems based on CatReNet
Home-page: https://github.com/JanRitschel/catpynet
Author: Jan Ritschel
Author-email: jan.ritschel@outlook.de
License: Apache 2.0
Requires-Python: >=3.11
License-File: LICENSE
License-File: AUTHORS
